MANIFEST.in
README.rst
setup.py
rapidsms_httprouter/__init__.py
rapidsms_httprouter/admin.py
rapidsms_httprouter/models.py
rapidsms_httprouter/router.py
rapidsms_httprouter/tasks.py
rapidsms_httprouter/tests.py
rapidsms_httprouter/urls.py
rapidsms_httprouter/views.py
rapidsms_httprouter.egg-info/PKG-INFO
rapidsms_httprouter.egg-info/SOURCES.txt
rapidsms_httprouter.egg-info/dependency_links.txt
rapidsms_httprouter.egg-info/not-zip-safe
rapidsms_httprouter.egg-info/requires.txt
rapidsms_httprouter.egg-info/top_level.txt
rapidsms_httprouter/migrations/0001_initial.py
rapidsms_httprouter/migrations/0001_initial.pyc
rapidsms_httprouter/migrations/0002_auto__add_field_message_updated.py
rapidsms_httprouter/migrations/0002_auto__add_field_message_updated.pyc
rapidsms_httprouter/migrations/0003_auto__add_deliveryerror__add_field_message_sent__add_field_message_del.py
rapidsms_httprouter/migrations/0003_auto__add_deliveryerror__add_field_message_sent__add_field_message_del.pyc
rapidsms_httprouter/migrations/__init__.py
rapidsms_httprouter/migrations/__init__.pyc
rapidsms_httprouter/static/rapidsms_httprouter/in.png
rapidsms_httprouter/static/rapidsms_httprouter/nav-bg.gif
rapidsms_httprouter/static/rapidsms_httprouter/out.png
rapidsms_httprouter/static/rapidsms_httprouter/stylesheets/admin.css
rapidsms_httprouter/static/rapidsms_httprouter/stylesheets/console.css
rapidsms_httprouter/templates/router/index.html
rapidsms_httprouter/templates/router/admin/change_list.html