Metadata-Version: 1.0
Name: rapidsms-httprouter
Version: 2.0.3
Summary: Provides HTTP endpoints for a RapidSMS router, doing all handling in the Django thread.
Home-page: http://github.com/nyaruka/rapidsms-httprouter
Author: Nicolas Pottier, Eric Newcomer
Author-email: code@nyaruka.com
License: BSD
Download-URL: http://github.com/nyaruka/rapidsms-httprouter/downloads
Platform: UNKNOWN
Classifier: Development Status :: 4 - Beta
Classifier: Environment :: Web Environment
Classifier: Intended Audience :: Developers
Classifier: License :: OSI Approved :: BSD License
Classifier: Operating System :: OS Independent
Classifier: Programming Language :: Python
Classifier: Framework :: Django
